fy_core/__init__.py
fy_core/base/__init__.py
fy_core/base/flow_base.py
fy_core/py.typed
fy_core-0.1.2.dist-info/LICENSE
fy_core-0.1.2.dist-info/METADATA
fy_core-0.1.2.dist-info/WHEEL
fy_core-0.1.2.dist-info/RECORD
