Metadata-Version: 2.1
Name: fy_core
Version: 0.1.2
Summary: Core classes for implementing Execution Flows in Python projects.
Author: Vinko Buble
Author-email: vinkobuble@gmail.com
Requires-Python: >=3.10,<3.14
Classifier: Programming Language :: Python :: 3
Classifier: Programming Language :: Python :: 3.10
Classifier: Programming Language :: Python :: 3.11
Classifier: Programming Language :: Python :: 3.12
